{"nodes": [{"id": "src_tests_wheel_templates_test_ts", "label": "wheel-templates.test.ts", "file_type": "code", "source_file": "src/__tests__/wheel-templates.test.ts", "source_location": "L1"}, {"id": "wheel_templates_test_isvalidcolor", "label": "isValidColor()", "file_type": "code", "source_file": "src/__tests__/wheel-templates.test.ts", "source_location": "L7"}], "edges": [{"source": "src_tests_wheel_templates_test_ts", "target": "vitest", "relation": "imports_from", "confidence": "EXTRACTED", "source_file": "src/__tests__/wheel-templates.test.ts", "source_location": "L1", "weight": 1.0}, {"source": "src_tests_wheel_templates_test_ts", "target": "wheel_templates", "relation": "imports_from", "confidence": "EXTRACTED", "source_file": "src/__tests__/wheel-templates.test.ts", "source_location": "L2", "weight": 1.0}, {"source": "src_tests_wheel_templates_test_ts", "target": "wheel_templates_test_isvalidcolor", "relation": "contains", "confidence": "EXTRACTED", "source_file": "src/__tests__/wheel-templates.test.ts", "source_location": "L7", "weight": 1.0}]}